telemetry_router/__init__.py
telemetry_router/_version.py
telemetry_router/application.py
telemetry_router/handlers.py
telemetry_router-0.1.20.data/data/etc/jupyter/jupyter_notebook_config.d/telemetry_router.json
telemetry_router-0.1.20.data/data/etc/jupyter/jupyter_server_config.d/telemetry_router.json
telemetry_router-0.1.20.data/data/share/jupyter/labextensions/telemetry-router/package.json
telemetry_router-0.1.20.data/data/share/jupyter/labextensions/telemetry-router/static/747.3ba83e0acd2b381f34b2.js
telemetry_router-0.1.20.data/data/share/jupyter/labextensions/telemetry-router/static/763.89204252de54eab1e086.js
telemetry_router-0.1.20.data/data/share/jupyter/labextensions/telemetry-router/static/remoteEntry.82409e8a182d3eaf2f01.js
telemetry_router-0.1.20.data/data/share/jupyter/labextensions/telemetry-router/static/style.js
telemetry_router-0.1.20.data/data/share/jupyter/labextensions/telemetry-router/static/third-party-licenses.json
telemetry_router-0.1.20.data/data/share/jupyter/labextensions/telemetry-router/install.json
telemetry_router-0.1.20.dist-info/METADATA
telemetry_router-0.1.20.dist-info/WHEEL
telemetry_router-0.1.20.dist-info/licenses/LICENSE
telemetry_router-0.1.20.dist-info/RECORD
